{
  "id": "3559854",
  "name": "司机端App",
  "font_family": "iconfont",
  "css_prefix_text": "icon-",
  "description": "",
  "glyphs": [
    {
      "icon_id": "30974954",
      "name": "duigou",
      "font_class": "duigou",
      "unicode": "e734",
      "unicode_decimal": 59188
    },
    {
      "icon_id": "30974955",
      "name": "close",
      "font_class": "close",
      "unicode": "e735",
      "unicode_decimal": 59189
    },
    {
      "icon_id": "30974956",
      "name": "bianji",
      "font_class": "bianji",
      "unicode": "e736",
      "unicode_decimal": 59190
    },
    {
      "icon_id": "30974957",
      "name": "boda",
      "font_class": "boda",
      "unicode": "e737",
      "unicode_decimal": 59191
    },
    {
      "icon_id": "30974958",
      "name": "daohang",
      "font_class": "daohang",
      "unicode": "e738",
      "unicode_decimal": 59192
    },
    {
      "icon_id": "30974959",
      "name": "erweima",
      "font_class": "erweima",
      "unicode": "e739",
      "unicode_decimal": 59193
    },
    {
      "icon_id": "30974960",
      "name": "shenglue",
      "font_class": "shenglue",
      "unicode": "e73a",
      "unicode_decimal": 59194
    },
    {
      "icon_id": "30974961",
      "name": "fuzhi",
      "font_class": "fuzhi",
      "unicode": "e73b",
      "unicode_decimal": 59195
    },
    {
      "icon_id": "30974962",
      "name": "bangzhu",
      "font_class": "bangzhu",
      "unicode": "e73c",
      "unicode_decimal": 59196
    },
    {
      "icon_id": "30974963",
      "name": "phone",
      "font_class": "phone",
      "unicode": "e73d",
      "unicode_decimal": 59197
    },
    {
      "icon_id": "30974964",
      "name": "guanbi",
      "font_class": "guanbi",
      "unicode": "e73e",
      "unicode_decimal": 59198
    },
    {
      "icon_id": "30974965",
      "name": "shanguang",
      "font_class": "shanguang",
      "unicode": "e73f",
      "unicode_decimal": 59199
    },
    {
      "icon_id": "30974966",
      "name": "shaixuan",
      "font_class": "shaixuan",
      "unicode": "e740",
      "unicode_decimal": 59200
    },
    {
      "icon_id": "30974967",
      "name": "delate",
      "font_class": "delate",
      "unicode": "e741",
      "unicode_decimal": 59201
    },
    {
      "icon_id": "30974968",
      "name": "check",
      "font_class": "check",
      "unicode": "e742",
      "unicode_decimal": 59202
    },
    {
      "icon_id": "30974969",
      "name": "jinggao",
      "font_class": "jinggao",
      "unicode": "e743",
      "unicode_decimal": 59203
    },
    {
      "icon_id": "30974970",
      "name": "password",
      "font_class": "password",
      "unicode": "e744",
      "unicode_decimal": 59204
    },
    {
      "icon_id": "30974971",
      "name": "guanyuwomen",
      "font_class": "guanyuwomen",
      "unicode": "e745",
      "unicode_decimal": 59205
    },
    {
      "icon_id": "30974972",
      "name": "qingchuhuancun",
      "font_class": "qingchuhuancun",
      "unicode": "e746",
      "unicode_decimal": 59206
    },
    {
      "icon_id": "30974973",
      "name": "photo",
      "font_class": "photo",
      "unicode": "e747",
      "unicode_decimal": 59207
    },
    {
      "icon_id": "30974974",
      "name": "xuanzhong",
      "font_class": "xuanzhong",
      "unicode": "e748",
      "unicode_decimal": 59208
    },
    {
      "icon_id": "30974975",
      "name": "shuaixn",
      "font_class": "shuaixn",
      "unicode": "e749",
      "unicode_decimal": 59209
    },
    {
      "icon_id": "30974976",
      "name": "mima",
      "font_class": "mima",
      "unicode": "e74a",
      "unicode_decimal": 59210
    },
    {
      "icon_id": "30974977",
      "name": "roundclose:2",
      "font_class": "a-roundclose2",
      "unicode": "e74b",
      "unicode_decimal": 59211
    },
    {
      "icon_id": "30974978",
      "name": "zhongdian",
      "font_class": "zhongdian",
      "unicode": "e74c",
      "unicode_decimal": 59212
    },
    {
      "icon_id": "30974979",
      "name": "xiangxia",
      "font_class": "xiangxia",
      "unicode": "e74d",
      "unicode_decimal": 59213
    },
    {
      "icon_id": "30974980",
      "name": "zhanghu",
      "font_class": "zhanghu",
      "unicode": "e74e",
      "unicode_decimal": 59214
    },
    {
      "icon_id": "30974981",
      "name": "zhanghu 2",
      "font_class": "a-zhanghu2",
      "unicode": "e74f",
      "unicode_decimal": 59215
    },
    {
      "icon_id": "30974982",
      "name": "sousuo",
      "font_class": "sousuo",
      "unicode": "e750",
      "unicode_decimal": 59216
    },
    {
      "icon_id": "30974983",
      "name": "kefu",
      "font_class": "kefu",
      "unicode": "e751",
      "unicode_decimal": 59217
    },
    {
      "icon_id": "30974984",
      "name": "zhaoxiangji",
      "font_class": "zhaoxiangji",
      "unicode": "e752",
      "unicode_decimal": 59218
    },
    {
      "icon_id": "30974985",
      "name": "roundclose",
      "font_class": "roundclose",
      "unicode": "e753",
      "unicode_decimal": 59219
    },
    {
      "icon_id": "30974986",
      "name": "weixuanzhong",
      "font_class": "weixuanzhong",
      "unicode": "e754",
      "unicode_decimal": 59220
    },
    {
      "icon_id": "30974987",
      "name": "zhuang",
      "font_class": "zhuang",
      "unicode": "e755",
      "unicode_decimal": 59221
    },
    {
      "icon_id": "30974988",
      "name": "zhankai",
      "font_class": "zhankai",
      "unicode": "e756",
      "unicode_decimal": 59222
    },
    {
      "icon_id": "30974989",
      "name": "shewnfenzheng",
      "font_class": "shewnfenzheng",
      "unicode": "e757",
      "unicode_decimal": 59223
    },
    {
      "icon_id": "30974990",
      "name": "qingchu",
      "font_class": "qingchu",
      "unicode": "e758",
      "unicode_decimal": 59224
    },
    {
      "icon_id": "30974991",
      "name": "suodingmima",
      "font_class": "suodingmima",
      "unicode": "e759",
      "unicode_decimal": 59225
    },
    {
      "icon_id": "30974992",
      "name": "shenfenzheng",
      "font_class": "shenfenzheng",
      "unicode": "e75a",
      "unicode_decimal": 59226
    },
    {
      "icon_id": "30974993",
      "name": "Wechat",
      "font_class": "Wechat",
      "unicode": "e75b",
      "unicode_decimal": 59227
    },
    {
      "icon_id": "30974994",
      "name": "touxiang",
      "font_class": "touxiang",
      "unicode": "e75c",
      "unicode_decimal": 59228
    },
    {
      "icon_id": "30974995",
      "name": "yundan",
      "font_class": "yundan",
      "unicode": "e75d",
      "unicode_decimal": 59229
    },
    {
      "icon_id": "30974996",
      "name": "yanzhengma",
      "font_class": "yanzhengma",
      "unicode": "e75e",
      "unicode_decimal": 59230
    },
    {
      "icon_id": "30974997",
      "name": "tongzhishezhi",
      "font_class": "tongzhishezhi",
      "unicode": "e75f",
      "unicode_decimal": 59231
    },
    {
      "icon_id": "30974998",
      "name": "xie",
      "font_class": "xie",
      "unicode": "e760",
      "unicode_decimal": 59232
    },
    {
      "icon_id": "30974999",
      "name": "congyezigezheng",
      "font_class": "congyezigezheng",
      "unicode": "e761",
      "unicode_decimal": 59233
    },
    {
      "icon_id": "30975000",
      "name": "shalou",
      "font_class": "shalou",
      "unicode": "e762",
      "unicode_decimal": 59234
    },
    {
      "icon_id": "30975006",
      "name": "打开",
      "font_class": "dakai",
      "unicode": "e763",
      "unicode_decimal": 59235
    },
    {
      "icon_id": "30975007",
      "name": "关闭",
      "font_class": "guanbi1",
      "unicode": "e764",
      "unicode_decimal": 59236
    }
  ]
}
